{"date":"2014-06-25T11:07:12.527Z","name":"ashwini.bramhasa@gmail.com","title":"Ashwini Bramhasa","account":"prmsh99@gmail.com","protocol":"gtalk","isChat":false}
{"date":"2014-06-25T11:07:13.000Z","who":"ashwini.bramhasa@gmail.com/ANDROID68a13a","text":"Work kadu classes","flags":["incoming"],"alias":"Ashwini Bramhasa"}
{"date":"2014-06-25T11:07:49.000Z","who":"ashwini.bramhasa@gmail.com/ANDROID68a13a","text":"Ippude exam pettaru","flags":["incoming"],"alias":"Ashwini Bramhasa"}
{"date":"2014-06-25T11:08:41.000Z","who":"ashwini.bramhasa@gmail.com/ANDROID68a13a","text":"Surprise test","flags":["incoming"],"alias":"Ashwini Bramhasa"}
{"date":"2014-06-25T11:18:32.000Z","who":"prmsh99@gmail.com/ThunderbirE9F7423E","text":"test aah?????","flags":["outgoing"]}
{"date":"2014-06-25T11:18:42.000Z","who":"prmsh99@gmail.com/ThunderbirE9F7423E","text":"inthaki ela rasav mari","flags":["outgoing"]}
{"date":"2014-06-25T11:18:55.000Z","who":"prmsh99@gmail.com/ThunderbirE9F7423E","text":"inthaki freshersl andhravalu ekkuva andi unnara","flags":["outgoing"]}
{"date":"2014-06-25T11:19:07.000Z","who":"prmsh99@gmail.com/ThunderbirE9F7423E","text":"ekkuva mandi unnara","flags":["outgoing"]}
