{"date":"2014-06-30T07:58:21.528Z","name":"praveenreddymora@gmail.com","title":"mora praveen kumar reddy","account":"prmsh99@gmail.com","protocol":"gtalk","isChat":false}
{"date":"2014-06-30T07:58:22.000Z","who":"praveenreddymora@gmail.com/smgmailwF9D488B9","text":"ha needi?","flags":["incoming"],"alias":"mora praveen kumar reddy"}
{"date":"2014-06-30T08:03:31.000Z","who":"praveenreddymora@gmail.com/smgmailwF9D488B9","text":"thinesa ra ..inthaku mundhe ","flags":["incoming"],"alias":"mora praveen kumar reddy"}
{"date":"2014-06-30T08:03:51.000Z","who":"praveenreddymora@gmail.com/smgmailwF9D488B9","text":"ippude vacha baytiki velli","flags":["incoming"],"alias":"mora praveen kumar reddy"}
{"date":"2014-06-30T08:05:34.000Z","who":"prmsh99@gmail.com/Thunderbir6E4EB812","text":"oh kk","flags":["outgoing"]}
{"date":"2014-06-30T08:06:28.000Z","who":"praveenreddymora@gmail.com/smgmailwF9D488B9","text":"kk ","flags":["incoming"],"alias":"mora praveen kumar reddy"}
